dramacool/__init__.py
dramacool/episode_scraper.py
dramacool/final_link.py
dramacool/link_scraper.py
dramacool/main.py
dramacool/ydl.py
dramacool-0.4.dist-info/LICENSE
dramacool-0.4.dist-info/METADATA
dramacool-0.4.dist-info/WHEEL
dramacool-0.4.dist-info/entry_points.txt
dramacool-0.4.dist-info/top_level.txt
dramacool-0.4.dist-info/RECORD
