Metadata-Version: 2.1
Name: dramacool
Version: 0.4
Summary: A simple cli package that lets you download asian webseries/dramas/movies from dramacool website.
Home-page: https://github.com/nandan645/dramacool-dl
Author: Abhi Nandan
Author-email: nandan645@protonmail.com
Classifier: Programming Language :: Python :: 3
Classifier: License :: OSI Approved :: MIT License
Classifier: Operating System :: OS Independent
License-File: LICENSE
Requires-Dist: requests
Requires-Dist: beautifulsoup4
Requires-Dist: yt-dlp
Requires-Dist: aria2
